[
  {
    "text": "to tell", 
    "key": "kaT kaTayati"
  }, 
  {
    "text": "to wash", 
    "key": "kzal kzAlayati"
  }, 
  {
    "text": "to count", 
    "key": "gaR gaRayati"
  }, 
  {
    "text": "to proclaim", 
    "key": "Guz Gozayati"
  }, 
  {
    "text": "to think", 
    "key": "cint cintayati"
  }, 
  {
    "text": "to steal", 
    "key": "cur corayati"
  }, 
  {
    "text": "to cover", 
    "key": "Cad CAdayati"
  }, 
  {
    "text": "to punish", 
    "key": "daRq daRqayati"
  }, 
  {
    "text": "to owe", 
    "key": "Df DArayati"
  }, 
  {
    "text": "to protect", 
    "key": "pAl pAlayati"
  }, 
  {
    "text": "to oppress", 
    "key": "pIq pIqayati"
  }, 
  {
    "text": "to adore", 
    "key": "pUj pUjayati"
  }, 
  {
    "text": "to eat", 
    "key": "Bakz Bakzayati"
  }, 
  {
    "text": "to adorn", 
    "key": "BUz BUzayati"
  }, 
  {
    "text": "to arrange", 
    "key": "rac racayati"
  }, 
  {
    "text": "to console", 
    "key": "sAntv sAntvayati"
  }, 
  {
    "text": "to long for (+Dative)", 
    "key": "spfh spfhayati"
  }, 
  {
    "text": "to cross", 
    "key": "ati-kram atikrAmyati"
  }, 
  {
    "text": "to obtain", 
    "key": "aDi-gam aDigacCati"
  }, 
  {
    "text": "to follow", 
    "key": "anu-sf anusarati"
  }, 
  {
    "text": "to depart", 
    "key": "apa-car apacarati"
  }, 
  {
    "text": "to attack", 
    "key": "aBi-DAv aBiDAvati"
  }, 
  {
    "text": "to burn down", 
    "key": "ava-dah avadahati"
  }, 
  {
    "text": "to bring", 
    "key": "A-nI Anayati"
  }, 
  {
    "text": "to arise", 
    "key": "ud-BU udBavati"
  }, 
  {
    "text": "to sit", 
    "key": "upa-viS upaviSati"
  }, 
  {
    "text": "over, beyond", 
    "key": "ati"
  }, 
  {
    "text": "near,unto", 
    "key": "aDi"
  }, 
  {
    "text": "after,along", 
    "key": "anu"
  }, 
  {
    "text": "away from", 
    "key": "apa"
  }, 
  {
    "text": "towards", 
    "key": "aBi"
  }, 
  {
    "text": "down", 
    "key": "ava"
  }, 
  {
    "text": "unto,back", 
    "key": "A"
  }, 
  {
    "text": "up,forth", 
    "key": "ud"
  }, 
  {
    "text": "near", 
    "key": "upa"
  }, 
  {
    "text": "under", 
    "key": "ni"
  }, 
  {
    "text": "away,out", 
    "key": "nis"
  }, 
  {
    "text": "round,about", 
    "key": "pari"
  }, 
  {
    "text": "forward", 
    "key": "pra"
  }, 
  {
    "text": "towards,against", 
    "key": "prati"
  }, 
  {
    "text": "apart,without", 
    "key": "vi"
  }, 
  {
    "text": "together,fully", 
    "key": "sam"
  }
]